hvac_quotes_mcp/__init__.py
hvac_quotes_mcp/__main__.py
hvac_quotes_mcp/distributor_db.py
hvac_quotes_mcp/email_sender.py
hvac_quotes_mcp/models.py
hvac_quotes_mcp/quote_tracker.py
hvac_quotes_mcp/rfq_manager.py
hvac_quotes_mcp/server.py
hvac_quotes_mcp-1.0.0.dist-info/METADATA
hvac_quotes_mcp-1.0.0.dist-info/WHEEL
hvac_quotes_mcp-1.0.0.dist-info/entry_points.txt
hvac_quotes_mcp-1.0.0.dist-info/RECORD
