Metadata-Version: 2.4
Name: hvac-quotes-mcp
Version: 1.0.0
Summary: HVAC equipment RFQ management via MCP for Claude Desktop
Project-URL: Homepage, https://github.com/wmarceau/hvac-quotes-mcp
Project-URL: Repository, https://github.com/wmarceau/hvac-quotes-mcp
Author-email: William Marceau <william@marceausolutions.com>
License: MIT
Keywords: claude,contractor,equipment,hvac,mcp,quotes,rfq
Classifier: Development Status :: 4 - Beta
Classifier: Intended Audience :: Developers
Classifier: License :: OSI Approved :: MIT License
Classifier: Programming Language :: Python :: 3
Classifier: Programming Language :: Python :: 3.10
Classifier: Programming Language :: Python :: 3.11
Classifier: Programming Language :: Python :: 3.12
Requires-Python: >=3.10
